unifonter.py
unifonter-0.5.0.dist-info/entry_points.txt
unifonter-0.5.0.dist-info/LICENSE
unifonter-0.5.0.dist-info/WHEEL
unifonter-0.5.0.dist-info/METADATA
unifonter-0.5.0.dist-info/RECORD
