Metadata-Version: 2.1
Name: unifonter
Version: 0.5.0
Summary: A filter that tries to make ASCII fancy with the help of Unicode
Home-page: https://github.com/chipaca/unifonter
License: GPL-3.0-or-later
Author: John R. Lenton
Author-email: jlenton@gmail.com
Requires-Python: >=3.6,<4.0
Classifier: License :: OSI Approved :: GNU General Public License v3 or later (GPLv3+)
Classifier: Operating System :: OS Independent
Classifier: Programming Language :: Python :: 3
Classifier: Programming Language :: Python :: 3.6
Classifier: Programming Language :: Python :: 3.7
Classifier: Programming Language :: Python :: 3.8
Classifier: Programming Language :: Python :: 3.9
Classifier: Topic :: Text Processing :: Filters
Project-URL: Repository, https://github.com/chipaca/unifonter
